odoo10_addon_server_env_connector_magento-10.0.1.0.0.99.dev4-py2.7-nspkg.pth
odoo/addons/server_env_connector_magento/README.rst
odoo/addons/server_env_connector_magento/__init__.py
odoo/addons/server_env_connector_magento/__manifest__.py
odoo/addons/server_env_connector_magento/i18n/server_env_connector_magento.pot
odoo/addons/server_env_connector_magento/models/__init__.py
odoo/addons/server_env_connector_magento/models/magento_backend.py
odoo/addons/server_env_connector_magento/static/description/icon.png
odoo10_addon_server_env_connector_magento-10.0.1.0.0.99.dev4.dist-info/METADATA
odoo10_addon_server_env_connector_magento-10.0.1.0.0.99.dev4.dist-info/RECORD
odoo10_addon_server_env_connector_magento-10.0.1.0.0.99.dev4.dist-info/WHEEL
odoo10_addon_server_env_connector_magento-10.0.1.0.0.99.dev4.dist-info/namespace_packages.txt
odoo10_addon_server_env_connector_magento-10.0.1.0.0.99.dev4.dist-info/top_level.txt
